machinelogic/__init__.py
machinelogic/decorators/__init__.py
machinelogic/decorators/future_api.py
machinelogic/decorators/undocumented.py
machinelogic/decorators/tests/__init__.py
machinelogic/decorators/tests/test_future_api.py
machinelogic/decorators/tests/test_undocumented.py
machinelogic/ivention/__init__.py
machinelogic/ivention/event_listener.py
machinelogic/ivention/exception.py
machinelogic/ivention/handle.py
machinelogic/ivention/iac_motor.py
machinelogic/ivention/iactuator.py
machinelogic/ivention/iactuator_group.py
machinelogic/ivention/ibag_gripper.py
machinelogic/ivention/icamera.py
machinelogic/ivention/idigital_input.py
machinelogic/ivention/idigital_io_shared.py
machinelogic/ivention/idigital_output.py
machinelogic/ivention/iestop.py
machinelogic/ivention/imachine.py
machinelogic/ivention/imachine_motion.py
machinelogic/ivention/ipath_follower.py
machinelogic/ivention/ipneumatic.py
machinelogic/ivention/irobot.py
machinelogic/ivention/machine_configuration.py
machinelogic/ivention/mqtt_client.py
machinelogic/ivention/tests/__init__.py
machinelogic/ivention/tests/test_event_listener.py
machinelogic/ivention/tests/test_idigital_input.py
machinelogic/ivention/tests/test_idigital_output.py
machinelogic/ivention/tests/test_imachine.py
machinelogic/ivention/tests/test_ipath_follower.py
machinelogic/ivention/tests/test_mqtt_client.py
machinelogic/ivention/types/__init__.py
machinelogic/ivention/types/ac_motor_details.py
machinelogic/ivention/types/actuator_details.py
machinelogic/ivention/types/bag_gripper_details.py
machinelogic/ivention/types/input_details.py
machinelogic/ivention/types/output_details.py
machinelogic/ivention/types/path_follower_status.py
machinelogic/ivention/types/path_follower_tool.py
machinelogic/ivention/types/pneumatic_details.py
machinelogic/ivention/util/__init__.py
machinelogic/ivention/util/inheritance.py
machinelogic/machinelogic/__init__.py
machinelogic/machinelogic/ac_motor.py
machinelogic/machinelogic/actuator.py
machine_code_python_sdk-1.13.0.dist-info/METADATA
machine_code_python_sdk-1.13.0.dist-info/WHEEL
machine_code_python_sdk-1.13.0.dist-info/top_level.txt
machine_code_python_sdk-1.13.0.dist-info/RECORD
