Metadata-Version: 2.1
Name: machine-code-python-sdk
Version: 1.13.0
Summary: MachineCode SDK for Vention hardware
Home-page: https://vention.io/resources/guides/machinelogic-python-programming-514
Author: VentionCo
Author-email: vention-sw-ci@vention.cc
Classifier: Operating System :: POSIX :: Linux
Classifier: Programming Language :: Python :: 3.5
Requires-Python: >=3.6
Requires-Dist: miros ==4.2.1
Requires-Dist: paho-mqtt ==1.5.1
Requires-Dist: types-requests ==2.28.11
Requires-Dist: requests ==2.31.0
Requires-Dist: typing-extensions ==4.6.3
Requires-Dist: parameterized
Requires-Dist: numpy ==1.24.2
Requires-Dist: roslibpy ==1.4.2
Requires-Dist: scipy ==1.11.1
Requires-Dist: zope.interface ==5.5.2
